fostrom/__init__.py
fostrom/agent.py
fostrom/dl-agent.sh
fostrom/errors.py
fostrom/fostrom.py
fostrom/http_unix.py
fostrom/mailbox.py
fostrom/py.typed
fostrom/sse.py
fostrom/utils.py
fostrom-0.0.17.dist-info/METADATA
fostrom-0.0.17.dist-info/WHEEL
fostrom-0.0.17.dist-info/licenses/LICENSE
fostrom-0.0.17.dist-info/RECORD
