Metadata-Version: 2.4
Name: fostrom
Version: 0.0.17
Summary: Fostrom Device SDK
Project-URL: Fostrom, https://fostrom.io
Project-URL: SDK Docs, https://fostrom.io/docs/sdk/py
Author-email: Fostrom <support@fostrom.io>
License: Apache-2.0
License-File: LICENSE
Keywords: actions,cloud,datapoint,device,fleet,fostrom,hardware,iot,message,mqtt,raspberry,sdk,websockets
Classifier: Development Status :: 4 - Beta
Classifier: Intended Audience :: Developers
Classifier: License :: OSI Approved :: Apache Software License
Classifier: Operating System :: OS Independent
Classifier: Programming Language :: Python :: 3
Classifier: Programming Language :: Python :: 3.10
Classifier: Programming Language :: Python :: 3.11
Classifier: Programming Language :: Python :: 3.12
Classifier: Programming Language :: Python :: 3.13
Classifier: Programming Language :: Python :: 3.14
Classifier: Programming Language :: Python :: 3.15
Classifier: Typing :: Typed
Requires-Python: >=3.10
